MANIFEST.in
README.rst
setup.py
bin/mbx
mbx.egg-info/PKG-INFO
mbx.egg-info/SOURCES.txt
mbx.egg-info/dependency_links.txt
mbx.egg-info/requires.txt
mbx.egg-info/top_level.txt
olib/__init__.py
olib/bus.py
olib/clk.py
olib/dbs.py
olib/edt.py
olib/err.py
olib/evt.py
olib/fnd.py
olib/hdl.py
olib/itr.py
olib/ldr.py
olib/nms.py
olib/obj.py
olib/opt.py
olib/prs.py
olib/tbl.py
olib/thr.py
olib/tms.py
olib/trc.py
olib/trm.py
olib/url.py
olib/utl.py
olib/zzz.py