Metadata-Version: 1.1
Name: mbx
Version: 1
Summary: mailbox scanner
Home-page: https://github.com/bthate67/mbx
Author: Bart Thate
Author-email: bthate67@gmail.com
License: Public Domain
Platform: UNKNOWN
Classifier: Development Status :: 4 - Beta
Classifier: License :: Public Domain
Classifier: Operating System :: Unix
Classifier: Programming Language :: Python
Classifier: Topic :: Utilities
